wave_api/__init__.py
wave_api/create_portfolio/__init__.py
wave_api/create_portfolio/create_portfolio.py
wave_api/create_portfolio/df_converter.py
wave_api/date_settings/__init__.py
wave_api/date_settings/date_settings.py
wave_api/date_settings/wave_date_manager.py
wave_api/get_google_sheets_data/__init__.py
wave_api/get_google_sheets_data/get_google_sheets_data.py
wave_api/google_login/__init__.py
wave_api/google_login/google_login.py
wave_api/options/__init__.py
wave_api/options/options.py
wave_api-0.1.2.dist-info/LICENSE.txt
wave_api-0.1.2.dist-info/METADATA
wave_api-0.1.2.dist-info/WHEEL
wave_api-0.1.2.dist-info/top_level.txt
wave_api-0.1.2.dist-info/RECORD
