Metadata-Version: 2.1
Name: wave-api
Version: 0.1.2
Summary: API for Wave Google Sheets
Home-page: https://github.com/jininvt/wave-api
Author: jininvt
Author-email: james@wizconsultancy.com
License: MIT
Download-URL: https://github.com/jininvt/wave-api/archive/v0.1.2.tar.gz
Keywords: Wave Accounting,Wave API
Platform: UNKNOWN
Classifier: Development Status :: 3 - Alpha
Classifier: Intended Audience :: Developers
Classifier: Topic :: Software Development :: Build Tools
Classifier: License :: OSI Approved :: MIT License
Classifier: Programming Language :: Python :: 3.8
Classifier: Programming Language :: Python :: 3.9
Requires-Dist: cachetools (==4.2.1)
Requires-Dist: certifi (==2020.12.5)
Requires-Dist: chardet (==4.0.0)
Requires-Dist: google-api-core (==1.26.0)
Requires-Dist: google-api-python-client (==1.12.8)
Requires-Dist: google-auth (==1.27.0)
Requires-Dist: google-auth-httplib2 (==0.0.4)
Requires-Dist: google-auth-oauthlib (==0.4.2)
Requires-Dist: googleapis-common-protos (==1.53.0)
Requires-Dist: httplib2 (==0.19.0)
Requires-Dist: idna (==2.10)
Requires-Dist: numpy (==1.20.1)
Requires-Dist: oauthlib (==3.1.0)
Requires-Dist: packaging (==20.9)
Requires-Dist: pandas (==1.2.2)
Requires-Dist: protobuf (==3.15.3)
Requires-Dist: pyasn1 (==0.4.8)
Requires-Dist: pyasn1-modules (==0.2.8)
Requires-Dist: pyparsing (==2.4.7)
Requires-Dist: python-dateutil (==2.8.1)
Requires-Dist: pytz (==2021.1)
Requires-Dist: requests (==2.25.1)
Requires-Dist: requests-oauthlib (==1.3.0)
Requires-Dist: rsa (==4.7.2)
Requires-Dist: six (==1.15.0)
Requires-Dist: uritemplate (==3.0.1)
Requires-Dist: urllib3 (==1.26.3)
